{
  "collectionName": "components_sections_cta_sections",
  "info": {
    "displayName": "cta-section",
    "icon": "connector"
  },
  "options": {},
  "attributes": {
    "title": {
      "type": "string"
    },
    "subtitle": {
      "type": "string"
    },
    "buttonText": {
      "type": "string"
    },
    "buttonLink": {
      "type": "string"
    },
    "buttonVariant": {
      "type": "enumeration",
      "enum": [
        "primary",
        "secondary",
        "outline"
      ]
    },
    "buttonSize": {
      "type": "enumeration",
      "enum": [
        "small",
        "medium",
        "large"
      ]
    },
    "openInNewTab": {
      "type": "boolean"
    },
    "backgroundColor": {
      "type": "enumeration",
      "enum": [
        "light",
        "dark",
        "primary",
        "secondary"
      ]
    },
    "textAlignment": {
      "type": "enumeration",
      "enum": [
        "left",
        "center",
        "right"
      ]
    }
  },
  "config": {}
}
